{"persistenceType":"ANALYTICAL","mailEnabled":false,"roles":["all"],"templateTechnicalName":"tableoneconfgexport1","useExtract":true,"filters":{},"templateGcsFileName":"tableoneconfg_tableoneconfgexport1_template.json","tableName":"Table One Confg","fileTypes":["csv"],"templateName":"Table One Confg export 1","mailSourceFile":"tableoneconfg_tableoneconfgexport1.json","tableId":"6e102486-037b-440b-af18-ba8380138546","header":{"1":{"Sid":"Sid"},"2":{"Created By":"Created By"},"3":{"Created Date":"Created Date"},"4":{"Modified By":"Modified By"},"5":{"Modified Date":"Modified Date"},"6":{"Sync Time":"Sync Time"},"7":{"value1":"value1"},"8":{"value2":"value2"}},"batchSize":0,"exportId":"Table One Confg export 1","tableTechnicalName":"TableOneConfg","headerFieldTypeMap":{"Modified By":"String","Modified Date":"Date","Sync Time":"Date","value2":"String","Created Date":"Date","value1":"String","Created By":"String","Sid":"String"}}